setup.py
django_filepages.egg-info/PKG-INFO
django_filepages.egg-info/SOURCES.txt
django_filepages.egg-info/dependency_links.txt
django_filepages.egg-info/not-zip-safe
django_filepages.egg-info/top_level.txt
filepages/__init__.py
filepages/models.py
filepages/tests.py
filepages/urls.py
filepages/views.py