Metadata-Version: 1.0
Name: django-filepages
Version: 1.1.0
Summary: Route urls to file system templates in Django.
Home-page: https://github.com/prestontimmons/django-filepages
Author: Preston Timmons
Author-email: prestontimmons@gmail.com
License: UNKNOWN
Platform: UNKNOWN
